gsm/__init__.py
gsm/exceptions.py
gsm/utils.py
gsm/db/__init__.py
gsm/db/__init__.pyc
gsm/db/qf.py
gsm/db/qf.pyc
gsm-2.1.data/scripts/gsm
gsm-2.1.dist-info/DESCRIPTION.rst
gsm-2.1.dist-info/METADATA
gsm-2.1.dist-info/RECORD
gsm-2.1.dist-info/WHEEL
gsm-2.1.dist-info/metadata.json
gsm-2.1.dist-info/top_level.txt
