Metadata-Version: 2.0
Name: gsm
Version: 2.1
Summary: The Global Sky Model (GSM)
Home-page: https://github.com/bartscheers/gsm
Author: Bart Scheers
Author-email: bartscheers@gmail.com
License: UNKNOWN
Platform: UNKNOWN
Requires-Dist: numpy
Requires-Dist: six
Requires-Dist: pymonetdb
